{
    "latitude": 45.77,
    "longitude": 4.84,
    "timezone": "Europe/Paris",
    "currently": {
        "time": 1610319600,
        "summary": "Clear",
        "icon": "clear-night",
        "precipIntensity": 0,
        "precipProbability": 0,
        "temperature": -2.52,
        "apparentTemperature": -5.69,
        "dewPoint": -4.77,
        "humidity": 0.85,
        "pressure": 1022,
        "windSpeed": 8.04,
        "windGust": 19.67,
        "windBearing": 325,
        "cloudCover": 0.24,
        "uvIndex": 0,
        "visibility": 16.093,
        "ozone": 314.4
    },
    "hourly": {
        "summary": "Partly cloudy throughout the day.",
        "icon": "partly-cloudy-day",
        "data": [
            {
                "time": 1610319600,
                "summary": "Clear",
                "icon": "clear-night",
                "precipIntensity": 0,
                "precipProbability": 0,
                "temperature": -2.52,
                "apparentTemperature": -5.69,
                "dewPoint": -4.77,
                "humidity": 0.85,
                "pressure": 1022,
                "windSpeed": 8.04,
                "windGust": 19.67,
                "windBearing": 325,
                "cloudCover": 0.24,
                "uvIndex": 0,
                "visibility": 16.093,
                "ozone": 314.4
            },
            {
                "time": 1610323200,
                "summary": "Clear",
                "icon": "clear-night",
                "precipIntensity": 0,
                "precipProbability": 0,
                "temperature": -2.95,
                "apparentTemperature": -6.07,
                "dewPoint": -5.01,
                "humidity": 0.86,
                "pressure": 1021.8,
                "windSpeed": 7.68,
                "windGust": 18.61,
                "windBearing": 320,
                "cloudCover": 0.25,
                "uvIndex": 0,
                "visibility": 16.093,
                "ozone": 314.6
            },
            {
                "time": 1610326800,
                "summary": "Partly Cloudy",
                "icon": "partly-cloudy-night",
                "precipIntensity": 0,
                "precipProbability": 0,
                "temperature": -2.42,
                "apparentTemperature": -4.97,
                "dewPoint": -4.56,
                "humidity": 0.85,
                "pressure": 1022.2,
                "windSpeed": 6.4,
                "windGust": 17.69,
                "windBearing": 304,
                "cloudCover": 0.37,
                "uvIndex": 0,
                "visibility": 16.093,
                "ozone": 315.8
            },
            {
                "time": 1610330400,
                "summary": "Partly Cloudy",
                "icon": "partly-cloudy-night",
                "precipIntensity": 0,
                "precipProbability": 0,
                "temperature": -2.97,
                "apparentTemperature": -5.94,
                "dewPoint": -5.16,
                "humidity": 0.85,
                "pressure": 1022.5,
                "windSpeed": 7.26,
                "windGust": 17.67,
                "windBearing": 311,
                "cloudCover": 0.45,
                "uvIndex": 0,
                "visibility": 16.093,
                "ozone": 316.1
            },
            {
                "time": 1610334000,
                "summary": "Partly Cloudy",
                "icon": "partly-cloudy-night",
                "precipIntensity": 0,
                "precipProbability": 0,
                "temperature": -3.49,
                "apparentTemperature": -6.76,
                "dewPoint": -5.7,
                "humidity": 0.85,
                "pressure": 1022.6,
                "windSpeed": 7.83,
                "windGust": 17.97,
                "windBearing": 315,
                "cloudCover": 0.55,
                "uvIndex": 0,
                "visibility": 16.093,
                "ozone": 314.9
            },
            {
                "time": 1610337600,
                "summary": "Mostly Cloudy",
                "icon": "partly-cloudy-night",
                "precipIntensity": 0,
                "precipProbability": 0,
                "temperature": -3.91,
                "apparentTemperature": -7.15,
                "dewPoint": -6.22,
                "humidity": 0.84,
                "pressure": 1022.9,
                "windSpeed": 7.57,
                "windGust": 17.23,
                "windBearing": 315,
                "cloudCover": 0.6,
                "uvIndex": 0,
                "visibility": 16.093,
                "ozone": 314.8
            },
            {
                "time": 1610341200,
                "summary": "Mostly Cloudy",
                "icon": "partly-cloudy-night",
                "precipIntensity": 0,
                "precipProbability": 0,
                "temperature": -3.93,
                "apparentTemperature": -7.43,
                "dewPoint": -6.12,
                "humidity": 0.85,
                "pressure": 1023.2,
                "windSpeed": 8.27,
                "windGust": 17.93,
                "windBearing": 320,
                "cloudCover": 0.63,
                "uvIndex": 0,
                "visibility": 16.093,
                "ozone": 314.3
            },
            {
                "time": 1610344800,
                "summary": "Mostly Cloudy",
                "icon": "partly-cloudy-night",
                "precipIntensity": 0,
                "precipProbability": 0,
                "temperature": -4.28,
                "apparentTemperature": -7.78,
                "dewPoint": -6.42,
                "humidity": 0.85,
                "pressure": 1023.9,
                "windSpeed": 8.08,
                "windGust": 17.76,
                "windBearing": 319,
                "cloudCover": 0.63,
                "uvIndex": 0,
                "visibility": 16.093,
                "ozone": 318.6
            },
            {
                "time": 1610348400,
                "summary": "Partly Cloudy",
                "icon": "partly-cloudy-night",
                "precipIntensity": 0,
                "precipProbability": 0,
                "temperature": -4.43,
                "apparentTemperature": -7.9,
                "dewPoint": -6.46,
                "humidity": 0.86,
                "pressure": 1024.2,
                "windSpeed": 7.94,
                "windGust": 18.3,
                "windBearing": 323,
                "cloudCover": 0.59,
                "uvIndex": 0,
                "visibility": 16.093,
                "ozone": 319.4
            },
            {
                "time": 1610352000,
                "summary": "Partly Cloudy",
                "icon": "partly-cloudy-day",
                "precipIntensity": 0,
                "precipProbability": 0,
                "temperature": -4.55,
                "apparentTemperature": -7.7,
                "dewPoint": -6.28,
                "humidity": 0.88,
                "pressure": 1024.6,
                "windSpeed": 7.06,
                "windGust": 16.56,
                "windBearing": 328,
                "cloudCover": 0.54,
                "uvIndex": 0,
                "visibility": 16.093,
                "ozone": 324
            },
            {
                "time": 1610355600,
                "summary": "Partly Cloudy",
                "icon": "partly-cloudy-day",
                "precipIntensity": 0,
                "precipProbability": 0,
                "temperature": -4.11,
                "apparentTemperature": -7.28,
                "dewPoint": -6.39,
                "humidity": 0.84,
                "pressure": 1025,
                "windSpeed": 7.3,
                "windGust": 17.97,
                "windBearing": 333,
                "cloudCover": 0.49,
                "uvIndex": 0,
                "visibility": 16.093,
                "ozone": 325.2
            },
            {
                "time": 1610359200,
                "summary": "Partly Cloudy",
                "icon": "partly-cloudy-day",
                "precipIntensity": 0,
                "precipProbability": 0,
                "temperature": -2.72,
                "apparentTemperature": -5.82,
                "dewPoint": -6.34,
                "humidity": 0.76,
                "pressure": 1025.2,
                "windSpeed": 7.75,
                "windGust": 17.83,
                "windBearing": 343,
                "cloudCover": 0.53,
                "uvIndex": 1,
                "visibility": 16.093,
                "ozone": 319.4
            },
            {
                "time": 1610362800,
                "summary": "Partly Cloudy",
                "icon": "partly-cloudy-day",
                "precipIntensity": 0,
                "precipProbability": 0,
                "temperature": -1.4,
                "apparentTemperature": -4.74,
                "dewPoint": -5.96,
                "humidity": 0.71,
                "pressure": 1024.5,
                "windSpeed": 9.21,
                "windGust": 19.37,
                "windBearing": 356,
                "cloudCover": 0.55,
                "uvIndex": 1,
                "visibility": 16.093,
                "ozone": 312.8
            },
            {
                "time": 1610366400,
                "summary": "Partly Cloudy",
                "icon": "partly-cloudy-day",
                "precipIntensity": 0,
                "precipProbability": 0,
                "temperature": 0.12,
                "apparentTemperature": -2.97,
                "dewPoint": -5.73,
                "humidity": 0.65,
                "pressure": 1024.1,
                "windSpeed": 9.32,
                "windGust": 18.69,
                "windBearing": 5,
                "cloudCover": 0.57,
                "uvIndex": 1,
                "visibility": 16.093,
                "ozone": 306.1
            },
            {
                "time": 1610370000,
                "summary": "Clear",
                "icon": "clear-day",
                "precipIntensity": 0,
                "precipProbability": 0,
                "temperature": 1.6,
                "apparentTemperature": -1,
                "dewPoint": -5.22,
                "humidity": 0.61,
                "pressure": 1023.4,
                "windSpeed": 8.56,
                "windGust": 18.1,
                "windBearing": 1,
                "cloudCover": 0.29,
                "uvIndex": 1,
                "visibility": 16.093,
                "ozone": 303.2
            },
            {
                "time": 1610373600,
                "summary": "Clear",
                "icon": "clear-day",
                "precipIntensity": 0,
                "precipProbability": 0,
                "temperature": 2.12,
                "apparentTemperature": -0.81,
                "dewPoint": -5.21,
                "humidity": 0.58,
                "pressure": 1023.1,
                "windSpeed": 10.18,
                "windGust": 18.75,
                "windBearing": 6,
                "cloudCover": 0.28,
                "uvIndex": 1,
                "visibility": 16.093,
                "ozone": 305.1
            },
            {
                "time": 1610377200,
                "summary": "Clear",
                "icon": "clear-day",
                "precipIntensity": 0.0051,
                "precipProbability": 0.02,
                "precipType": "rain",
                "temperature": 2.11,
                "apparentTemperature": -0.76,
                "dewPoint": -4.93,
                "humidity": 0.6,
                "pressure": 1023.3,
                "windSpeed": 9.95,
                "windGust": 19.89,
                "windBearing": 5,
                "cloudCover": 0.3,
                "uvIndex": 0,
                "visibility": 16.093,
                "ozone": 305.8
            },
            {
                "time": 1610380800,
                "summary": "Clear",
                "icon": "clear-day",
                "precipIntensity": 0.0051,
                "precipProbability": 0.02,
                "precipType": "rain",
                "temperature": 1.06,
                "apparentTemperature": -1.52,
                "dewPoint": -4.92,
                "humidity": 0.64,
                "pressure": 1024.1,
                "windSpeed": 8.12,
                "windGust": 14.43,
                "windBearing": 354,
                "cloudCover": 0.14,
                "uvIndex": 0,
                "visibility": 16.093,
                "ozone": 300.4
            },
            {
                "time": 1610384400,
                "summary": "Clear",
                "icon": "clear-night",
                "precipIntensity": 0,
                "precipProbability": 0,
                "temperature": -0.63,
                "apparentTemperature": -3,
                "dewPoint": -5.16,
                "humidity": 0.71,
                "pressure": 1024.7,
                "windSpeed": 6.67,
                "windGust": 10.33,
                "windBearing": 331,
                "cloudCover": 0.01,
                "uvIndex": 0,
                "visibility": 16.093,
                "ozone": 296.1
            },
            {
                "time": 1610388000,
                "summary": "Clear",
                "icon": "clear-night",
                "precipIntensity": 0,
                "precipProbability": 0,
                "temperature": -1.82,
                "apparentTemperature": -3.81,
                "dewPoint": -5.55,
                "humidity": 0.76,
                "pressure": 1025.3,
                "windSpeed": 5.35,
                "windGust": 10.32,
                "windBearing": 313,
                "cloudCover": 0.01,
                "uvIndex": 0,
                "visibility": 16.093,
                "ozone": 300.1
            },
            {
                "time": 1610391600,
                "summary": "Clear",
                "icon": "clear-night",
                "precipIntensity": 0,
                "precipProbability": 0,
                "temperature": -2.44,
                "apparentTemperature": -4.33,
                "dewPoint": -5.86,
                "humidity": 0.77,
                "pressure": 1025.5,
                "windSpeed": 4.98,
                "windGust": 8.94,
                "windBearing": 308,
                "cloudCover": 0.04,
                "uvIndex": 0,
                "visibility": 16.093,
                "ozone": 297.4
            },
            {
                "time": 1610395200,
                "summary": "Clear",
                "icon": "clear-night",
                "precipIntensity": 0,
                "precipProbability": 0,
                "temperature": -2.78,
                "apparentTemperature": -2.78,
                "dewPoint": -5.92,
                "humidity": 0.79,
                "pressure": 1025.8,
                "windSpeed": 4.56,
                "windGust": 7.59,
                "windBearing": 299,
                "cloudCover": 0.01,
                "uvIndex": 0,
                "visibility": 16.093,
                "ozone": 296.6
            },
            {
                "time": 1610398800,
                "summary": "Clear",
                "icon": "clear-night",
                "precipIntensity": 0,
                "precipProbability": 0,
                "temperature": -3.14,
                "apparentTemperature": -3.14,
                "dewPoint": -6.4,
                "humidity": 0.78,
                "pressure": 1026,
                "windSpeed": 4.17,
                "windGust": 5.88,
                "windBearing": 290,
                "cloudCover": 0.01,
                "uvIndex": 0,
                "visibility": 16.093,
                "ozone": 291.1
            },
            {
                "time": 1610402400,
                "summary": "Clear",
                "icon": "clear-night",
                "precipIntensity": 0,
                "precipProbability": 0,
                "temperature": -3.25,
                "apparentTemperature": -3.25,
                "dewPoint": -6.51,
                "humidity": 0.78,
                "pressure": 1026.1,
                "windSpeed": 4.7,
                "windGust": 8.59,
                "windBearing": 337,
                "cloudCover": 0.05,
                "uvIndex": 0,
                "visibility": 16.093,
                "ozone": 293.3
            }
        ]
    },
    "daily": {
        "data": [
            {
                "time": 1610319600,
                "summary": "Partly cloudy throughout the day.",
                "icon": "partly-cloudy-day",
                "sunriseTime": 1610349660,
                "sunsetTime": 1610381940,
                "moonPhase": 0.95,
                "precipIntensity": 0.0017,
                "precipIntensityMax": 0.0053,
                "precipIntensityMaxTime": 1610378700,
                "precipProbability": 0.03,
                "precipType": "snow",
                "precipAccumulation": 0,
                "temperatureHigh": 2.49,
                "temperatureHighTime": 1610375640,
                "temperatureLow": -3.86,
                "temperatureLowTime": 1610408040,
                "apparentTemperatureHigh": -0.71,
                "apparentTemperatureHighTime": 1610376120,
                "apparentTemperatureLow": -4.37,
                "apparentTemperatureLowTime": 1610391060,
                "dewPoint": -5.7,
                "humidity": 0.77,
                "pressure": 1024,
                "windSpeed": 7.42,
                "windGust": 20.08,
                "windGustTime": 1610376540,
                "windBearing": 333,
                "cloudCover": 0.35,
                "uvIndex": 1,
                "uvIndexTime": 1610366220,
                "visibility": 16.093,
                "ozone": 309.4,
                "temperatureMin": -4.83,
                "temperatureMinTime": 1610351400,
                "temperatureMax": 2.49,
                "temperatureMaxTime": 1610375640,
                "apparentTemperatureMin": -7.9,
                "apparentTemperatureMinTime": 1610348040,
                "apparentTemperatureMax": -0.71,
                "apparentTemperatureMaxTime": 1610376120
            }
        ]
    },
    "flags": {
        "sources": [
            "cmc",
            "gfs",
            "icon",
            "isd",
            "madis"
        ],
        "nearest-station": 9.332,
        "units": "ca"
    },
    "offset": 1
}